ask_git/__init__.py
ask_git/cli.py
ask_git/ollama_client.py
ask_git/prompt_builder.py
ask_git/commands/__init__.py
ask_git/commands/explain.py
ask_git/commands/pr_summary.py
ask_git/commands/summary.py
ask_git/commands/why.py
ask_git/git_utils/__init__.py
ask_git/git_utils/blame.py
ask_git/git_utils/diff.py
ask_git/git_utils/log.py
ask_git/git_utils/utils.py
ask_git-0.1.4.dist-info/METADATA
ask_git-0.1.4.dist-info/WHEEL
ask_git-0.1.4.dist-info/entry_points.txt
ask_git-0.1.4.dist-info/top_level.txt
ask_git-0.1.4.dist-info/RECORD
