Metadata-Version: 2.4
Name: ask-git
Version: 0.1.4
Summary: Ask Git anything — Powered by Ollama.
Author-email: Aayush Rajesh Jadhav <aayushrj22@gmail.com>
License: MIT
Requires-Python: >=3.9
Requires-Dist: typer[all]
Requires-Dist: requests
Requires-Dist: gitpython
Requires-Dist: rich
